Metadata-Version: 2.1
Name: shameless
Version: 0.0.2
Summary: Shameless browser automation
Home-page: https://github.com/seyoungsong/shameless
Author: Seyoung Song
Author-email: seyoung@macbook.local
License: UNKNOWN
Platform: UNKNOWN
Classifier: Programming Language :: Python :: 3
Classifier: License :: OSI Approved :: MIT License
Classifier: Operating System :: OS Independent
Requires-Python: >=3.6
